mlopspypi/__init__.py
mlopspypi/main.py
mlopspypi-0.1.1.dist-info/METADATA
mlopspypi-0.1.1.dist-info/WHEEL
mlopspypi-0.1.1.dist-info/licenses/LICENSE
mlopspypi-0.1.1.dist-info/RECORD
