Metadata-Version: 2.4
Name: mlopspypi
Version: 0.1.1
Summary: A small reusable Python utilities package
Project-URL: Homepage, https://github.com/kimhabkhun/mlopspypi
Project-URL: Bug Tracker, https://github.com/kimhabkhun/mlopspypi/issues
Author-email: MLOps Team <mlopsteam@gmail.com>
License: MIT
License-File: LICENSE
Keywords: example,reusable,utility
Classifier: License :: OSI Approved :: MIT License
Classifier: Operating System :: OS Independent
Classifier: Programming Language :: Python :: 3
Requires-Python: >=3.8
